{"cameraMode":{"drawMode":0,"name":"Shaded","section":"Shading Mode"},"sceneLighting":false,"audioPlay":false,"sceneViewState":{"showFog":true,"showMaterialUpdate":false,"showSkybox":false,"showFlares":true,"showImageEffects":true,"showParticleSystems":true},"in2DMode":false,"pivot":{"x":0.0012858957052230836,"y":-0.019649744033813478,"z":-0.23320317268371583},"rotation":{"x":-0.002997260307893157,"y":-0.7855693697929382,"z":0.003761276602745056,"w":-0.6188077330589294},"size":1.026742696762085,"orthographic":false}